coolstuff/ComprehensibilityAnalysis.py
coolstuff/FunctionalityAnalysis.py
coolstuff/Interface.py
coolstuff/RobustnessAnalysis.py
coolstuff/__init__.py
coolstuff/dataloader.py
coolstuff/extra_puzzle.py
coolstuff/get_models.py
coolstuff/main.py
coolstuff/models.py
coolstuff/task.py
coolstuff/test_art.py
coolstuff/test_stuff.py
coolstuff/training_cifar-10.py
coolstuff-1.0.2.dist-info/LICENSE
coolstuff-1.0.2.dist-info/METADATA
coolstuff-1.0.2.dist-info/WHEEL
coolstuff-1.0.2.dist-info/top_level.txt
coolstuff-1.0.2.dist-info/RECORD
