Metadata-Version: 2.1
Name: coolstuff
Version: 1.0.2
Summary: ML-analysis
Home-page: UNKNOWN
Author: Raymond
License: UNKNOWN
Keywords: cool,stuff
Platform: UNKNOWN
Classifier: Programming Language :: Python :: 3
Classifier: License :: OSI Approved :: MIT License
Classifier: Operating System :: OS Independent
Classifier: Development Status :: 3 - Alpha
Requires-Dist: pandas
Requires-Dist: torchvision
Requires-Dist: torch
Requires-Dist: adversarial-robustness-toolbox
Requires-Dist: sklearn
Requires-Dist: tensorflow
Requires-Dist: captum
Requires-Dist: plotly
